<annotation>
	<folder>c0</folder>
	<filename>000469.jpg</filename>
	<path>D:\datasets\datasets\final\images\c0\000469.jpg</path>
	<source>
		<database>Unknown</database>
	</source>
	<size>
		<width>500</width>
		<height>500</height>
		<depth>3</depth>
	</size>
	<segmented>0</segmented>
	<object>
		<name>rock</name>
		<pose>Unspecified</pose>
		<truncated>0</truncated>
		<difficult>0</difficult>
		<bndbox>
			<xmin>136</xmin>
			<ymin>158</ymin>
			<xmax>326</xmax>
			<ymax>410</ymax>
		</bndbox>
	</object>
</annotation>
